tactic_client_lib/VERSION
tactic_client_lib/VERSION_API
tactic_client_lib/__init__.py
tactic_client_lib/cgapp.py
tactic_client_lib/tactic.zip
tactic_client_lib/tactic_server_stub.py
tactic_client_lib/application/__init__.py
tactic_client_lib/application/common/__init__.py
tactic_client_lib/application/common/application.py
tactic_client_lib/application/common/application_old.py
tactic_client_lib/application/common/introspect.py
tactic_client_lib/application/common/node_data.py
tactic_client_lib/application/common/session.py
tactic_client_lib/application/common/tactic_node_util.py
tactic_client_lib/application/maya/__init__.py
tactic_client_lib/application/maya/maya_app.py
tactic_client_lib/common/__init__.py
tactic_client_lib/common/common.py
tactic_client_lib/common/upload_multipart.py
tactic_client_lib/interpreter/__init__.py
tactic_client_lib/interpreter/callback.py
tactic_client_lib/interpreter/examples.py
tactic_client_lib/interpreter/handler.py
tactic_client_lib/interpreter/interpreter.py
tactic_client_lib/interpreter/pipeline.py
tactic_client_lib/scm/__init__.py
tactic_client_lib/scm/delegate.py
tactic_client_lib/scm/perforce.py
tactic_client_lib/scm/scm_impl.py
tactic_client_lib/scm/scm_test.py
tactic_client_lib/scm/subversion.py
tactic_client_lib/scm/tactic_impl.py
tactic_client_lib/test/__init__.py
tactic_client_lib/test/handler.py
tactic_client_lib-4.8.data/scripts/create_project.py
tactic_client_lib-4.8.data/scripts/get_ticket.py
tactic_client_lib-4.8.dist-info/LICENSE
tactic_client_lib-4.8.dist-info/METADATA
tactic_client_lib-4.8.dist-info/WHEEL
tactic_client_lib-4.8.dist-info/top_level.txt
tactic_client_lib-4.8.dist-info/RECORD
